{"errors":[],"warnings":[],"namedChunkGroups":{"app":{"chunks":[7,6,2],"assets":["webpack-runtime-f558b1b5aaec751c8434.js","webpack-runtime-f558b1b5aaec751c8434.js.map","framework-868c53fff4771b0bde98.js","framework-868c53fff4771b0bde98.js.map","app-2197910089dda60a14e9.js","app-2197910089dda60a14e9.js.map"],"children":{},"childAssets":{}},"component---src-pages-404-js":{"chunks":[1,0,3],"assets":["styles.335f9ef6cf0b504eec63.css","styles-c2fe8482057191dca484.js","styles-c2fe8482057191dca484.js.map","commons-eb7eaf31bce14688add7.js","commons-eb7eaf31bce14688add7.js.map","component---src-pages-404-js-852bd3a5faea7629c57d.js","component---src-pages-404-js-852bd3a5faea7629c57d.js.map"],"children":{},"childAssets":{}},"component---src-pages-index-js":{"chunks":[1,0,4],"assets":["styles.335f9ef6cf0b504eec63.css","styles-c2fe8482057191dca484.js","styles-c2fe8482057191dca484.js.map","commons-eb7eaf31bce14688add7.js","commons-eb7eaf31bce14688add7.js.map","component---src-pages-index-js-76e31029d7407a112ea9.js","component---src-pages-index-js-76e31029d7407a112ea9.js.map"],"children":{},"childAssets":{}},"component---src-pages-using-typescript-tsx":{"chunks":[1,0,5],"assets":["styles.335f9ef6cf0b504eec63.css","styles-c2fe8482057191dca484.js","styles-c2fe8482057191dca484.js.map","commons-eb7eaf31bce14688add7.js","commons-eb7eaf31bce14688add7.js.map","component---src-pages-using-typescript-tsx-16c9963c741c08852aff.js","component---src-pages-using-typescript-tsx-16c9963c741c08852aff.js.map"],"children":{},"childAssets":{}}},"assetsByChunkName":{"app":["webpack-runtime-f558b1b5aaec751c8434.js","framework-868c53fff4771b0bde98.js","app-2197910089dda60a14e9.js"],"component---src-pages-404-js":["styles.335f9ef6cf0b504eec63.css","styles-c2fe8482057191dca484.js","commons-eb7eaf31bce14688add7.js","component---src-pages-404-js-852bd3a5faea7629c57d.js"],"component---src-pages-index-js":["styles.335f9ef6cf0b504eec63.css","styles-c2fe8482057191dca484.js","commons-eb7eaf31bce14688add7.js","component---src-pages-index-js-76e31029d7407a112ea9.js"],"component---src-pages-using-typescript-tsx":["styles.335f9ef6cf0b504eec63.css","styles-c2fe8482057191dca484.js","commons-eb7eaf31bce14688add7.js","component---src-pages-using-typescript-tsx-16c9963c741c08852aff.js"]}}